jsonsh.py
jsonsh_utils.py
jsonshell-1.0.0.dist-info/LICENSE
jsonshell-1.0.0.dist-info/METADATA
jsonshell-1.0.0.dist-info/WHEEL
jsonshell-1.0.0.dist-info/entry_points.txt
jsonshell-1.0.0.dist-info/top_level.txt
jsonshell-1.0.0.dist-info/RECORD
