Metadata-Version: 2.1
Name: jsonshell
Version: 1.0.0
Summary: JSONShell, the easy way to navigate JSON objects in a shell-like environment
Author-email: Carl Furtado <carlzfurtado@gmail.com>
License: MIT License
Project-URL: Homepage, https://github.com/User0332/jsonshell
Requires-Python: >=3.9
License-File: LICENSE
Requires-Dist: anytree (>=2.8.0)
